sbibm/__init__.py
sbibm/__version__.py
sbibm/algorithms/__init__.py
sbibm/algorithms/elfi/__init__.py
sbibm/algorithms/elfi/bolfi.py
sbibm/algorithms/elfi/utils/__init__.py
sbibm/algorithms/elfi/utils/prior.py
sbibm/algorithms/elfi/utils/wrapper.py
sbibm/algorithms/pyabc/__init__.py
sbibm/algorithms/pyabc/pyabc_utils.py
sbibm/algorithms/pyabc/smcabc.py
sbibm/algorithms/pyabcranger/__init__.py
sbibm/algorithms/pyabcranger/abcranger_utils.py
sbibm/algorithms/pyabcranger/abcrf.py
sbibm/algorithms/pyro/__init__.py
sbibm/algorithms/pyro/mcmc.py
sbibm/algorithms/pyro/utils/__init__.py
sbibm/algorithms/pyro/utils/tensorboard.py
sbibm/algorithms/pytorch/__init__.py
sbibm/algorithms/pytorch/baseline_grid.py
sbibm/algorithms/pytorch/baseline_posterior.py
sbibm/algorithms/pytorch/baseline_prior.py
sbibm/algorithms/pytorch/baseline_rejection.py
sbibm/algorithms/pytorch/baseline_runtime.py
sbibm/algorithms/pytorch/baseline_sir.py
sbibm/algorithms/pytorch/utils/__init__.py
sbibm/algorithms/pytorch/utils/proposal.py
sbibm/algorithms/sbi/__init__.py
sbibm/algorithms/sbi/mcabc.py
sbibm/algorithms/sbi/sl.py
sbibm/algorithms/sbi/smcabc.py
sbibm/algorithms/sbi/snle.py
sbibm/algorithms/sbi/snpe.py
sbibm/algorithms/sbi/snre.py
sbibm/algorithms/sbi/utils.py
sbibm/metrics/__init__.py
sbibm/metrics/c2st.py
sbibm/metrics/ksd.py
sbibm/metrics/mmd.py
sbibm/metrics/moments.py
sbibm/metrics/mvn_kl.py
sbibm/metrics/ppc.py
sbibm/tasks/__init__.py
sbibm/tasks/simulator.py
sbibm/tasks/task.py
sbibm/tasks/bernoulli_glm/__init__.py
sbibm/tasks/bernoulli_glm/task.py
sbibm/tasks/bernoulli_glm/files/design_matrix.pt
sbibm/tasks/bernoulli_glm/files/stimulus_I.pt
sbibm/tasks/bernoulli_glm/files/stimulus_t.pt
sbibm/tasks/bernoulli_glm/files/num_observation_1/observation.csv
sbibm/tasks/bernoulli_glm/files/num_observation_1/observation_raw.csv
sbibm/tasks/bernoulli_glm/files/num_observation_1/observation_seed.csv
sbibm/tasks/bernoulli_glm/files/num_observation_1/reference_posterior_samples.csv.bz2
sbibm-1.1.0.dist-info/LICENSE
sbibm-1.1.0.dist-info/METADATA
sbibm-1.1.0.dist-info/WHEEL
sbibm-1.1.0.dist-info/top_level.txt
sbibm-1.1.0.dist-info/RECORD
