Metadata-Version: 2.1
Name: sbibm
Version: 1.1.0
Summary: Simulation-based inference benchmark
Home-page: https://github.com/sbi-benchmark/sbibm
Author: Jan-Matthis Lueckmann
Author-email: mail@jan-matthis.de
License: MIT
Platform: UNKNOWN
Classifier: License :: OSI Approved :: MIT License
Classifier: Intended Audience :: Developers
Classifier: Intended Audience :: Education
Classifier: Intended Audience :: Science/Research
Classifier: Operating System :: POSIX :: Linux
Classifier: Operating System :: MacOS :: MacOS X
Classifier: Programming Language :: Python
Classifier: Programming Language :: Python :: 3
Classifier: Programming Language :: Python :: 3.7
Classifier: Programming Language :: Python :: 3.8
Classifier: Programming Language :: Python :: 3.9
Requires-Python: >=3.7.0
Requires-Dist: autograd
Requires-Dist: elfi (>=0.7.6)
Requires-Dist: deneb
Requires-Dist: diffeqtorch
Requires-Dist: joblib
Requires-Dist: numpy
Requires-Dist: matplotlib
Requires-Dist: pandas (>=1.0.0)
Requires-Dist: pyabc (>=0.10.8)
Requires-Dist: pyabcranger (>=0.0.48)
Requires-Dist: sbi (<0.22.0,>=0.20.0)
Requires-Dist: pyro-ppl
Requires-Dist: scikit-learn
Requires-Dist: torch (>=1.8.0)
Requires-Dist: tqdm
Provides-Extra: dev
Requires-Dist: autoflake ; extra == 'dev'
Requires-Dist: black ; extra == 'dev'
Requires-Dist: flake8 ; extra == 'dev'
Requires-Dist: isort (>5.0.0) ; extra == 'dev'
Requires-Dist: ipdb ; extra == 'dev'
Requires-Dist: pytest ; extra == 'dev'
Requires-Dist: pytest-plt ; extra == 'dev'
Requires-Dist: typeguard ; extra == 'dev'
